nonebot_plugin_boardgamehelper/__init__.py
nonebot_plugin_boardgamehelper/config.py
nonebot_plugin_boardgamehelper/data_manager.py
nonebot_plugin_boardgamehelper/models.py
nonebot_plugin_boardgamehelper/post_func.py
nonebot_plugin_boardgamehelper/utils.py
nonebot_plugin_boardgamehelper/validator.py
nonebot_plugin_boardgamehelper-1.0.0.dist-info/licenses/LICENSE
nonebot_plugin_boardgamehelper-1.0.0.dist-info/METADATA
nonebot_plugin_boardgamehelper-1.0.0.dist-info/WHEEL
nonebot_plugin_boardgamehelper-1.0.0.dist-info/RECORD
