Metadata-Version: 2.4
Name: nonebot-plugin-boardgamehelper
Version: 1.0.0
Summary: 一个 NoneBot2 桌游约车助手插件，提供桌游群招募、发车、封车等功能。
License: BSD 3-Clause License
License-File: LICENSE
Author: Salted_Fish0208
Author-email: saltedfish0208@hotmail.com
Requires-Python: >=3.12,<4.0
Classifier: License :: Other/Proprietary License
Classifier: Programming Language :: Python :: 3
Classifier: Programming Language :: Python :: 3.12
Classifier: Programming Language :: Python :: 3.13
Classifier: Programming Language :: Python :: 3.14
Requires-Dist: nonebot-adapter-onebot (>=2.4.6,<3.0.0)
Requires-Dist: nonebot-plugin-alconna (>=0.60.3,<0.61.0)
Requires-Dist: nonebot-plugin-apscheduler (>=0.5.0,<0.6.0)
Requires-Dist: nonebot-plugin-localstore (>=0.7.4,<0.8.0)
Requires-Dist: nonebot2 (>=2.4.4,<3.0.0)
Requires-Dist: shortuuid (>=1.0.13,<2.0.0)
Requires-Dist: sqlalchemy (>=2.0.45,<3.0.0)
